SlickWiki-0.2.data/scripts/slick
slickwiki/__init__.py
slickwiki/templates.py
slickwiki/wikiapp.py
SlickWiki-0.2.dist-info/LICENSE
SlickWiki-0.2.dist-info/METADATA
SlickWiki-0.2.dist-info/WHEEL
SlickWiki-0.2.dist-info/top_level.txt
SlickWiki-0.2.dist-info/RECORD
