Metadata-Version: 2.1
Name: SlickWiki
Version: 0.2
Summary: Personal wiki tool
Home-page: UNKNOWN
Author: Jason R. Fruit
Author-email: jasonfruit@fastmail.com
License: MIT
Platform: UNKNOWN
Classifier: License :: OSI Approved :: MIT License
Classifier: Programming Language :: Python :: 3
Classifier: Development Status :: 4 - Beta
Classifier: Operating System :: POSIX
Classifier: Topic :: Office/Business
Requires-Dist: cherrypy
Requires-Dist: markdown
Requires-Dist: pystache
